sts1_sensor_libraries/ADXL345.py
sts1_sensor_libraries/AbstractSensor.py
sts1_sensor_libraries/BME688.py
sts1_sensor_libraries/BMM150.py
sts1_sensor_libraries/GUVA_C32.py
sts1_sensor_libraries/L3GD20H.py
sts1_sensor_libraries/TMP112.py
sts1_sensor_libraries/__init__.py
sts1_sensor_libraries/main.py
sts1_sensor_libraries/pysatdosclient.py
sts1_sensor_libraries-0.3.3.dist-info/METADATA
sts1_sensor_libraries-0.3.3.dist-info/WHEEL
sts1_sensor_libraries-0.3.3.dist-info/licenses/LICENSE
sts1_sensor_libraries-0.3.3.dist-info/RECORD
