Metadata-Version: 2.3
Name: sts1_sensor_libraries
Version: 0.3.3
Summary: A sensor library for the CubeSat STS1 (TU Wien Space Team).
Author-email: Simon Köfinger <simon.koefinger@spaceteam.at>, Florian Rohrer <florian.rohrer@spaceteam.at>
Requires-Python: >=3.13
Requires-Dist: pytest>=8.3.4
Requires-Dist: smbus2>=0.5.0
Requires-Dist: structlog>=24.4.0
